Workbook

Sheet Cotización 
A2: IMPOCRUZ EC S.A.S
A3: RUC: | B3: 993372361001 | G3: PROFORMA NÚMERO:
A4: DIRECCIÓN: | B4: Edif. The Point, of. 902 Puerto Santa Ana - Guayaquil
A5: CORREO: | B5: importadoracruzec@gmail.com
A6: PÁGINA WEB: | B6: https://www.impocruz.com/ | E6: CELULAR: | F6: 986397636
A8: CLIENTE: | H8: FECHA: | I8: 45842
A9: RUC: | G9: VALIDEZ DE LA OFERTA:
A10: DIRECCIÓN: | B10: Av. Ladrón de Guevara E11-253 y Andalucía | G10: TIEMPO DE ENTREGA:
A11: ATENCIÓN: | B11: Lorena López | G11: FORMA DE PAGO:
A12: CODIGO NECESIDAD DE CONTRATACION: | D12: NIC-1768183440001-2025-00083 | G12: GARANTÍA TÉCNICA:
A14: Ítem | B14: CPC | C14: Producto | F14: U/M | G14: Cantidad | H14: Costo unitario | I14: Costo total
A15: 1 | B15: 5327000115 | F15: U | I15: =H15*G15 -> 0
A16: 1 | F16: U | H16: =Costos!G15*1.75 -> 0 | I16: =H16*G16 -> 0
A17: =+A16+1 -> 2 | F17: U | H17: =Costos!G16*1.5 -> 0 | I17: =H17*G17 -> 0
A18: =+A17+1 -> 3 | F18: U | G18: =Costos!F17 -> 0 | H18: =Costos!G17*1.5 -> 0 | I18: =+G18*H18 -> 0
A19: =+A18+1 -> 4 | F19: U | H19: =Costos!G18*1.5 -> 0 | I19: =+G19*H19 -> 0
A20: =+A19+1 -> 5 | F20: U | H20: =Costos!G19*1.5 -> 0 | I20: =+G20*H20 -> 0
A21: =+A20+1 -> 6 | F21: U | H21: =Costos!G20*1.5 -> 0 | I21: =+G21*H21 -> 0
H26: Subtotal: | I26: =SUM(I15:I24) -> 0
A27: Ing. José Cruz Álvarez | H27: IVA 0%: | I27: 0
A28: Gerente General | H28: IVA 15%: | I28: =(I26*0.15) -> 0
A29: 908688633 | H29: Total: | I29: =(I26+I28) -> 0

Sheet Costos
A3: Sección de costos - NO SE DEBE INCLUIR ESTA SECCIÓN EN EL PDF A ENTREGAR A LA ENTIDAD
C6: LINK DEL PROCESO | G6: PAC | I6: Subtotal venta: | K6: ='Cotización '!I26 -> 0
J7: Ganancia: | K7: =('Cotización '!I26-H22) -> 0
J8: Inversión: | K8: =H22 -> 0
C10: Valor real: lo que nos cuesta el producto.
C11: Costo final: valor real + gestiones de importación en caso de que el producto se compre en el extranjero y los demás costos correspondientes a la gestión de entrega.
C13: Costo total: Costo final + cantidad.
C14: PRODUCTO | E14: VALOR REAL (UNITARIO) | F14: CANTIDAD | G14: COSTO FINAL (UNITARIO) | H14: COSTO TOTAL | J14: OPCIÓN RECOMENDADA
H15: =G15*F15 -> 0 | J15: OTRAS OPCIONES
H16: =G16*F16 -> 0
H17: =(G17*F17) -> 0
H18: =(G18*F18) -> 0
H19: =(G19*F19) -> 0
H20: =(G20*F20) -> 0
E21: =E15*F15 -> 0
H22: =SUM(H15:H20) -> 0 | I22: Valor de inversiòn total
E23: =K6-E21 -> 0
